{
  "lastUpdate": "2026-01-21T18:10:38.453910",
  "index": {
    "value": 17439.5,
    "change": 10.4,
    "changePercent": 0.06
  },
  "companies": [
    {
      "name": "Inditex",
      "ticker": "ITX",
      "sector": "Consumo",
      "price": 55.46,
      "change": -0.07,
      "marketCap": 172834.0
    },
    {
      "name": "Banco Santander",
      "ticker": "SAN",
      "sector": "Banca",
      "price": 10.32,
      "change": -0.04,
      "marketCap": 151639.0
    },
    {
      "name": "Iberdrola",
      "ticker": "IBE",
      "sector": "Energía",
      "price": 18.33,
      "change": -0.43,
      "marketCap": 122500.0
    },
    {
      "name": "BBVA",
      "ticker": "BBVA",
      "sector": "Banca",
      "price": 20.86,
      "change": 0.38,
      "marketCap": 118224.0
    },
    {
      "name": "Telefónica",
      "ticker": "TEF",
      "sector": "Telecom",
      "price": 3.24,
      "change": -1.67,
      "marketCap": 18262.0
    },
    {
      "name": "Repsol",
      "ticker": "REP",
      "sector": "Energía",
      "price": 16.14,
      "change": 2.77,
      "marketCap": 17901.0
    },
    {
      "name": "CaixaBank",
      "ticker": "CABK",
      "sector": "Banca",
      "price": 10.62,
      "change": 0.28,
      "marketCap": 74387.0
    },
    {
      "name": "Amadeus",
      "ticker": "AMS",
      "sector": "Tecnología",
      "price": 57.76,
      "change": -1.06,
      "marketCap": 24915.0
    },
    {
      "name": "Ferrovial",
      "ticker": "FER",
      "sector": "Construcción",
      "price": 56.68,
      "change": -0.32,
      "marketCap": 40525.0
    },
    {
      "name": "Naturgy",
      "ticker": "NTGY",
      "sector": "Energía",
      "price": 25.82,
      "change": 0.31,
      "marketCap": 24800.0
    },
    {
      "name": "ACS",
      "ticker": "ACS",
      "sector": "Construcción",
      "price": 92.65,
      "change": -0.59,
      "marketCap": 25170.0
    },
    {
      "name": "Endesa",
      "ticker": "ELE",
      "sector": "Energía",
      "price": 30.31,
      "change": 0.6,
      "marketCap": 31464.0
    },
    {
      "name": "Sabadell",
      "ticker": "SAB",
      "sector": "Banca",
      "price": 3.21,
      "change": 1.52,
      "marketCap": 16032.0
    },
    {
      "name": "Cellnex",
      "ticker": "CLNX",
      "sector": "Telecom",
      "price": 25.17,
      "change": -0.12,
      "marketCap": 17033.0
    },
    {
      "name": "IAG",
      "ticker": "IAG",
      "sector": "Transporte",
      "price": 4.82,
      "change": 2.99,
      "marketCap": 22003.0
    },
    {
      "name": "Grifols",
      "ticker": "GRF",
      "sector": "Farmacia",
      "price": 10.53,
      "change": 1.69,
      "marketCap": 7169.0
    },
    {
      "name": "Acciona",
      "ticker": "ANA",
      "sector": "Energía",
      "price": 176.6,
      "change": 0.51,
      "marketCap": 9625.0
    },
    {
      "name": "Bankinter",
      "ticker": "BKT",
      "sector": "Banca",
      "price": 14.23,
      "change": -0.39,
      "marketCap": 12784.0
    },
    {
      "name": "Aena",
      "ticker": "AENA",
      "sector": "Transporte",
      "price": 25.2,
      "change": -0.43,
      "marketCap": 37800.0
    },
    {
      "name": "Mapfre",
      "ticker": "MAP",
      "sector": "Seguros",
      "price": 3.86,
      "change": -1.23,
      "marketCap": 11811.0
    },
    {
      "name": "Acerinox",
      "ticker": "ACX",
      "sector": "Industrial",
      "price": 12.89,
      "change": 2.14,
      "marketCap": 3213.0
    },
    {
      "name": "Enagás",
      "ticker": "ENG",
      "sector": "Energía",
      "price": 13.55,
      "change": 0.26,
      "marketCap": 3522.0
    },
    {
      "name": "Unicaja",
      "ticker": "UNI",
      "sector": "Banca",
      "price": 2.81,
      "change": 0.5,
      "marketCap": 7207.0
    },
    {
      "name": "Meliá Hotels",
      "ticker": "MEL",
      "sector": "Turismo",
      "price": 7.43,
      "change": 0.07,
      "marketCap": 1635.0
    },
    {
      "name": "Sacyr",
      "ticker": "SCYR",
      "sector": "Construcción",
      "price": 3.92,
      "change": 0.15,
      "marketCap": 3098.0
    },
    {
      "name": "Solaria",
      "ticker": "SLR",
      "sector": "Energía",
      "price": 17.03,
      "change": 1.55,
      "marketCap": 2128.0
    },
    {
      "name": "Fluidra",
      "ticker": "FDR",
      "sector": "Industrial",
      "price": 25.34,
      "change": 0.32,
      "marketCap": 4812.0
    },
    {
      "name": "Rovi",
      "ticker": "ROVI",
      "sector": "Farmacia",
      "price": 72.15,
      "change": 0.07,
      "marketCap": 3690.0
    },
    {
      "name": "PharmaMar",
      "ticker": "PHM",
      "sector": "Farmacia",
      "price": 79.4,
      "change": -0.19,
      "marketCap": 1359.0
    },
    {
      "name": "Indra",
      "ticker": "IDR",
      "sector": "Tecnología",
      "price": 53.85,
      "change": -2.89,
      "marketCap": 9435.0
    },
    {
      "name": "ArcelorMittal",
      "ticker": "MTS",
      "sector": "Industrial",
      "price": 43.56,
      "change": 4.71,
      "marketCap": 33151.0
    },
    {
      "name": "Merlin Properties",
      "ticker": "MRL",
      "sector": "Inmobiliario",
      "price": 12.25,
      "change": 0.25,
      "marketCap": 6894.0
    },
    {
      "name": "Colonial",
      "ticker": "COL",
      "sector": "Inmobiliario",
      "price": 5.03,
      "change": -0.59,
      "marketCap": 3090.0
    },
    {
      "name": "Logista",
      "ticker": "LOG",
      "sector": "Distribución",
      "price": 30.78,
      "change": -0.77,
      "marketCap": 4064.0
    }
  ]
}